{
  "imageData": null,
  "fillColor": [
    255,
    0,
    0,
    128
  ],
  "lineColor": [
    0,
    255,
    0,
    128
  ],
  "imagePath": "11_1_i_h__20190625081123_88451136.jpg",
  "imageHeight": 576,
  "imageWidth": 704,
  "shapes": [
    {
      "line_color": null,
      "fill_color": null,
      "shape_type": "polygon",
      "label": "Private Car",
      "group_id": 0,
      "points": [
        [
          0,
          0
        ],
        [
          0,
          251
        ],
        [
          1,
          252
        ],
        [
          1,
          255
        ],
        [
          0,
          256
        ],
        [
          0,
          260
        ],
        [
          1,
          261
        ],
        [
          1,
          263
        ],
        [
          2,
          264
        ],
        [
          2,
          274
        ],
        [
          3,
          275
        ],
        [
          3,
          286
        ],
        [
          4,
          287
        ],
        [
          4,
          291
        ],
        [
          2,
          293
        ],
        [
          2,
          300
        ],
        [
          3,
          301
        ],
        [
          3,
          302
        ],
        [
          5,
          304
        ],
        [
          5,
          315
        ],
        [
          6,
          316
        ],
        [
          6,
          320
        ],
        [
          7,
          321
        ],
        [
          7,
          322
        ],
        [
          8,
          323
        ],
        [
          8,
          324
        ],
        [
          9,
          325
        ],
        [
          9,
          328
        ],
        [
          10,
          329
        ],
        [
          10,
          331
        ],
        [
          11,
          332
        ],
        [
          11,
          333
        ],
        [
          15,
          337
        ],
        [
          15,
          338
        ],
        [
          16,
          339
        ],
        [
          16,
          341
        ],
        [
          17,
          342
        ],
        [
          17,
          344
        ],
        [
          18,
          345
        ],
        [
          18,
          347
        ],
        [
          19,
          348
        ],
        [
          20,
          348
        ],
        [
          21,
          349
        ],
        [
          22,
          349
        ],
        [
          23,
          350
        ],
        [
          24,
          350
        ],
        [
          25,
          351
        ],
        [
          31,
          351
        ],
        [
          32,
          350
        ],
        [
          33,
          351
        ],
        [
          34,
          350
        ],
        [
          38,
          350
        ],
        [
          39,
          351
        ],
        [
          79,
          351
        ],
        [
          80,
          350
        ],
        [
          88,
          350
        ],
        [
          89,
          349
        ],
        [
          93,
          349
        ],
        [
          94,
          348
        ],
        [
          98,
          348
        ],
        [
          99,
          347
        ],
        [
          103,
          347
        ],
        [
          104,
          346
        ],
        [
          110,
          346
        ],
        [
          112,
          344
        ],
        [
          118,
          344
        ],
        [
          120,
          342
        ],
        [
          122,
          342
        ],
        [
          123,
          341
        ],
        [
          127,
          341
        ],
        [
          128,
          340
        ],
        [
          131,
          340
        ],
        [
          132,
          339
        ],
        [
          135,
          339
        ],
        [
          136,
          338
        ],
        [
          140,
          338
        ],
        [
          141,
          337
        ],
        [
          143,
          337
        ],
        [
          144,
          336
        ],
        [
          153,
          336
        ],
        [
          154,
          335
        ],
        [
          155,
          335
        ],
        [
          156,
          334
        ],
        [
          158,
          334
        ],
        [
          160,
          332
        ],
        [
          162,
          332
        ],
        [
          163,
          331
        ],
        [
          166,
          331
        ],
        [
          167,
          330
        ],
        [
          169,
          330
        ],
        [
          170,
          329
        ],
        [
          173,
          329
        ],
        [
          174,
          328
        ],
        [
          175,
          328
        ],
        [
          176,
          327
        ],
        [
          177,
          327
        ],
        [
          178,
          326
        ],
        [
          181,
          326
        ],
        [
          182,
          325
        ],
        [
          183,
          325
        ],
        [
          184,
          324
        ],
        [
          186,
          324
        ],
        [
          187,
          323
        ],
        [
          191,
          323
        ],
        [
          192,
          322
        ],
        [
          195,
          322
        ],
        [
          196,
          321
        ],
        [
          199,
          321
        ],
        [
          200,
          320
        ],
        [
          204,
          320
        ],
        [
          205,
          319
        ],
        [
          206,
          319
        ],
        [
          207,
          318
        ],
        [
          208,
          318
        ],
        [
          209,
          317
        ],
        [
          210,
          317
        ],
        [
          211,
          316
        ],
        [
          212,
          316
        ],
        [
          213,
          315
        ],
        [
          215,
          315
        ],
        [
          217,
          313
        ],
        [
          219,
          313
        ],
        [
          221,
          311
        ],
        [
          222,
          311
        ],
        [
          224,
          309
        ],
        [
          224,
          308
        ],
        [
          225,
          307
        ],
        [
          228,
          307
        ],
        [
          230,
          305
        ],
        [
          231,
          305
        ],
        [
          232,
          306
        ],
        [
          234,
          304
        ],
        [
          235,
          305
        ],
        [
          237,
          303
        ],
        [
          238,
          303
        ],
        [
          239,
          302
        ],
        [
          240,
          302
        ],
        [
          242,
          300
        ],
        [
          243,
          300
        ],
        [
          245,
          298
        ],
        [
          247,
          298
        ],
        [
          251,
          294
        ],
        [
          252,
          294
        ],
        [
          253,
          293
        ],
        [
          255,
          293
        ],
        [
          258,
          290
        ],
        [
          259,
          291
        ],
        [
          262,
          288
        ],
        [
          263,
          288
        ],
        [
          264,
          289
        ],
        [
          265,
          289
        ],
        [
          267,
          287
        ],
        [
          268,
          287
        ],
        [
          270,
          285
        ],
        [
          271,
          285
        ],
        [
          272,
          284
        ],
        [
          272,
          283
        ],
        [
          276,
          279
        ],
        [
          276,
          278
        ],
        [
          277,
          277
        ],
        [
          278,
          277
        ],
        [
          279,
          276
        ],
        [
          280,
          276
        ],
        [
          281,
          275
        ],
        [
          281,
          274
        ],
        [
          282,
          273
        ],
        [
          286,
          273
        ],
        [
          289,
          270
        ],
        [
          290,
          270
        ],
        [
          293,
          267
        ],
        [
          294,
          267
        ],
        [
          295,
          266
        ],
        [
          296,
          266
        ],
        [
          298,
          264
        ],
        [
          300,
          264
        ],
        [
          302,
          262
        ],
        [
          304,
          262
        ],
        [
          305,
          261
        ],
        [
          305,
          260
        ],
        [
          306,
          259
        ],
        [
          307,
          259
        ],
        [
          310,
          256
        ],
        [
          313,
          256
        ],
        [
          315,
          254
        ],
        [
          316,
          254
        ],
        [
          318,
          252
        ],
        [
          319,
          252
        ],
        [
          320,
          251
        ],
        [
          321,
          251
        ],
        [
          322,
          250
        ],
        [
          322,
          249
        ],
        [
          324,
          247
        ],
        [
          324,
          246
        ],
        [
          326,
          244
        ],
        [
          327,
          244
        ],
        [
          330,
          241
        ],
        [
          332,
          241
        ],
        [
          334,
          239
        ],
        [
          335,
          239
        ],
        [
          336,
          238
        ],
        [
          337,
          238
        ],
        [
          341,
          234
        ],
        [
          343,
          234
        ],
        [
          345,
          232
        ],
        [
          346,
          232
        ],
        [
          353,
          225
        ],
        [
          354,
          225
        ],
        [
          357,
          222
        ],
        [
          358,
          222
        ],
        [
          361,
          219
        ],
        [
          362,
          219
        ],
        [
          364,
          217
        ],
        [
          365,
          217
        ],
        [
          370,
          212
        ],
        [
          370,
          211
        ],
        [
          371,
          210
        ],
        [
          371,
          209
        ],
        [
          376,
          204
        ],
        [
          377,
          204
        ],
        [
          378,
          203
        ],
        [
          378,
          202
        ],
        [
          383,
          197
        ],
        [
          383,
          193
        ],
        [
          384,
          192
        ],
        [
          384,
          189
        ],
        [
          385,
          188
        ],
        [
          385,
          186
        ],
        [
          386,
          185
        ],
        [
          386,
          182
        ],
        [
          387,
          181
        ],
        [
          387,
          179
        ],
        [
          388,
          178
        ],
        [
          388,
          176
        ],
        [
          389,
          175
        ],
        [
          388,
          174
        ],
        [
          388,
          173
        ],
        [
          389,
          172
        ],
        [
          389,
          169
        ],
        [
          390,
          168
        ],
        [
          390,
          166
        ],
        [
          391,
          165
        ],
        [
          391,
          164
        ],
        [
          392,
          163
        ],
        [
          392,
          160
        ],
        [
          393,
          159
        ],
        [
          393,
          152
        ],
        [
          394,
          151
        ],
        [
          394,
          150
        ],
        [
          395,
          149
        ],
        [
          395,
          146
        ],
        [
          396,
          145
        ],
        [
          396,
          144
        ],
        [
          395,
          143
        ],
        [
          396,
          142
        ],
        [
          396,
          141
        ],
        [
          395,
          140
        ],
        [
          395,
          135
        ],
        [
          396,
          134
        ],
        [
          396,
          128
        ],
        [
          397,
          127
        ],
        [
          396,
          126
        ],
        [
          396,
          121
        ],
        [
          398,
          119
        ],
        [
          397,
          118
        ],
        [
          397,
          110
        ],
        [
          398,
          109
        ],
        [
          398,
          98
        ],
        [
          399,
          97
        ],
        [
          399,
          44
        ],
        [
          398,
          43
        ],
        [
          398,
          39
        ],
        [
          396,
          37
        ],
        [
          396,
          34
        ],
        [
          395,
          33
        ],
        [
          394,
          33
        ],
        [
          393,
          32
        ],
        [
          393,
          31
        ],
        [
          392,
          30
        ],
        [
          392,
          29
        ],
        [
          393,
          28
        ],
        [
          391,
          26
        ],
        [
          391,
          25
        ],
        [
          390,
          24
        ],
        [
          390,
          22
        ],
        [
          389,
          21
        ],
        [
          389,
          16
        ],
        [
          388,
          15
        ],
        [
          388,
          12
        ],
        [
          387,
          11
        ],
        [
          387,
          8
        ],
        [
          385,
          6
        ],
        [
          385,
          0
        ]
      ]
    }
  ]
}